CHANGELOG.txt
LICENSE.txt
MANIFEST.in
README.txt
setup.py
fazil/__init__.py
fazil.egg-info/PKG-INFO
fazil.egg-info/SOURCES.txt
fazil.egg-info/dependency_links.txt
fazil.egg-info/top_level.txt