Metadata-Version: 2.1
Name: fazil
Version: 0.0.1
Summary: A simple library developed by Fazil.
Home-page: UNKNOWN
Author: Mohamed Fazil
Author-email: mohamedfazil463@gmail.com
License: MIT
Keywords: fazil
Platform: UNKNOWN
Classifier: Development Status :: 5 - Production/Stable
Classifier: Intended Audience :: Education
Classifier: Operating System :: Microsoft :: Windows :: Windows 10
Classifier: License :: OSI Approved :: MIT License
Classifier: Programming Language :: Python :: 3
